PhD/__init__.py
PhD-0.1.dist-info/DESCRIPTION.rst
PhD-0.1.dist-info/METADATA
PhD-0.1.dist-info/RECORD
PhD-0.1.dist-info/WHEEL
PhD-0.1.dist-info/metadata.json
PhD-0.1.dist-info/top_level.txt
