Metadata-Version: 2.0
Name: PhD
Version: 0.1
Summary: A random test lib
Home-page: https://github.com/malramsay64/pip-phd
Author: Malcolm Ramsay
Author-email: malramsay64@gmail.com
License: MIT
Download-URL: https://github.com/malramsay64/php-phd/archive/0.1.tar.gz
Keywords: testing,logging,example
Platform: UNKNOWN
